<?xml version="1.0" encoding="UTF-8"?>
<Patch>

	<Operation Class="PatchOperationFindMod">
	<mods>
		<li>Insulation (Continued)</li>
	</mods>
	<match Class="PatchOperationSequence">
		<operations>

            <li Class="PatchOperationReplace">
                <xpath>Defs/ResearchProjectDef[defName="InsulationBiomass"]/researchViewX</xpath>
                <value>
                    <researchViewX>1.00</researchViewX>
                </value>
            </li>
            <li Class="PatchOperationReplace">
                <xpath>Defs/ResearchProjectDef[defName="InsulationBiomass"]/researchViewY</xpath>
                <value>
                    <researchViewY>49.00</researchViewY>
                </value>
            </li>
            <li Class="PatchOperationReplace">
                <xpath>Defs/ResearchProjectDef[defName="InsulationBiomass"]/tab</xpath>
                <value>
                    <tab>Buildings_SK</tab>
                </value>
            </li>
			<li Class="PatchOperationConditional">
				<xpath>/Defs/ResearchProjectDef[defName="InsulationBiomass"]/modExtensions/li[@Class="ResearchTreeSK.ResearchTreeSKModExtension"]</xpath>
				<nomatch Class="PatchOperationConditional">
					<xpath>/Defs/ResearchProjectDef[defName="InsulationBiomass"]/modExtensions</xpath>
					<match Class="PatchOperationAdd">
						<xpath>/Defs/ResearchProjectDef[defName="InsulationBiomass"]/modExtensions</xpath>
						<value>
							<li Class="ResearchTreeSK.ResearchTreeSKModExtension"></li>
						</value>
					</match>
					<nomatch Class="PatchOperationAdd">
						<xpath>/Defs/ResearchProjectDef[defName="InsulationBiomass"]</xpath>
						<value>
						<modExtensions>
							<li Class="ResearchTreeSK.ResearchTreeSKModExtension"></li>
						</modExtensions>
						</value>
					</nomatch>
				</nomatch>
			</li>

            <li Class="PatchOperationReplace">
                <xpath>Defs/ResearchProjectDef[defName="InsulationFibres"]/researchViewX</xpath>
                <value>
                    <researchViewX>7.00</researchViewX>
                </value>
            </li>
            <li Class="PatchOperationReplace">
                <xpath>Defs/ResearchProjectDef[defName="InsulationFibres"]/researchViewY</xpath>
                <value>
                    <researchViewY>49.00</researchViewY>
                </value>
            </li>
            <li Class="PatchOperationReplace">
                <xpath>Defs/ResearchProjectDef[defName="InsulationFibres"]/tab</xpath>
                <value>
                    <tab>Buildings_SK</tab>
                </value>
            </li>
			<li Class="PatchOperationConditional">
				<xpath>/Defs/ResearchProjectDef[defName="InsulationFibres"]/modExtensions/li[@Class="ResearchTreeSK.ResearchTreeSKModExtension"]</xpath>
				<nomatch Class="PatchOperationConditional">
					<xpath>/Defs/ResearchProjectDef[defName="InsulationFibres"]/modExtensions</xpath>
					<match Class="PatchOperationAdd">
						<xpath>/Defs/ResearchProjectDef[defName="InsulationFibres"]/modExtensions</xpath>
						<value>
							<li Class="ResearchTreeSK.ResearchTreeSKModExtension"></li>
						</value>
					</match>
					<nomatch Class="PatchOperationAdd">
						<xpath>/Defs/ResearchProjectDef[defName="InsulationFibres"]</xpath>
						<value>
						<modExtensions>
							<li Class="ResearchTreeSK.ResearchTreeSKModExtension"></li>
						</modExtensions>
						</value>
					</nomatch>
				</nomatch>
			</li>

            <li Class="PatchOperationReplace">
                <xpath>Defs/ResearchProjectDef[defName="InsulationPolymers"]/researchViewX</xpath>
                <value>
                    <researchViewX>12.00</researchViewX>
                </value>
            </li>
            <li Class="PatchOperationReplace">
                <xpath>Defs/ResearchProjectDef[defName="InsulationPolymers"]/researchViewY</xpath>
                <value>
                    <researchViewY>49.00</researchViewY>
                </value>
            </li>
            <li Class="PatchOperationReplace">
                <xpath>Defs/ResearchProjectDef[defName="InsulationPolymers"]/tab</xpath>
                <value>
                    <tab>Buildings_SK</tab>
                </value>
            </li>
			<li Class="PatchOperationConditional">
				<xpath>/Defs/ResearchProjectDef[defName="InsulationPolymers"]/modExtensions/li[@Class="ResearchTreeSK.ResearchTreeSKModExtension"]</xpath>
				<nomatch Class="PatchOperationConditional">
					<xpath>/Defs/ResearchProjectDef[defName="InsulationPolymers"]/modExtensions</xpath>
					<match Class="PatchOperationAdd">
						<xpath>/Defs/ResearchProjectDef[defName="InsulationPolymers"]/modExtensions</xpath>
						<value>
							<li Class="ResearchTreeSK.ResearchTreeSKModExtension"></li>
						</value>
					</match>
					<nomatch Class="PatchOperationAdd">
						<xpath>/Defs/ResearchProjectDef[defName="InsulationPolymers"]</xpath>
						<value>
						<modExtensions>
							<li Class="ResearchTreeSK.ResearchTreeSKModExtension"></li>
						</modExtensions>
						</value>
					</nomatch>
				</nomatch>
			</li>

            <li Class="PatchOperationReplace">
                <xpath>Defs/ResearchProjectDef[defName="InsulationHyper"]/researchViewX</xpath>
                <value>
                    <researchViewX>18.00</researchViewX>
                </value>
            </li>
            <li Class="PatchOperationReplace">
                <xpath>Defs/ResearchProjectDef[defName="InsulationHyper"]/researchViewY</xpath>
                <value>
                    <researchViewY>27.00</researchViewY>
                </value>
            </li>
            <li Class="PatchOperationReplace">
                <xpath>Defs/ResearchProjectDef[defName="InsulationHyper"]/tab</xpath>
                <value>
                    <tab>Buildings_SK</tab>
                </value>
            </li>
			<li Class="PatchOperationConditional">
				<xpath>/Defs/ResearchProjectDef[defName="InsulationHyper"]/modExtensions/li[@Class="ResearchTreeSK.ResearchTreeSKModExtension"]</xpath>
				<nomatch Class="PatchOperationConditional">
					<xpath>/Defs/ResearchProjectDef[defName="InsulationHyper"]/modExtensions</xpath>
					<match Class="PatchOperationAdd">
						<xpath>/Defs/ResearchProjectDef[defName="InsulationHyper"]/modExtensions</xpath>
						<value>
							<li Class="ResearchTreeSK.ResearchTreeSKModExtension"></li>
						</value>
					</match>
					<nomatch Class="PatchOperationAdd">
						<xpath>/Defs/ResearchProjectDef[defName="InsulationHyper"]</xpath>
						<value>
						<modExtensions>
							<li Class="ResearchTreeSK.ResearchTreeSKModExtension"></li>
						</modExtensions>
						</value>
					</nomatch>
				</nomatch>
			</li>

		</operations>
		</match>
    </Operation>	
</Patch>	